odoo8_addon_account_move_template-8.0.1.0.0.99.dev48-py3.8-nspkg.pth
odoo_addons/account_move_template/README.rst
odoo_addons/account_move_template/__init__.py
odoo_addons/account_move_template/__openerp__.py
odoo_addons/account_move_template/account_document_template.py
odoo_addons/account_move_template/account_move_template.py
odoo_addons/account_move_template/i18n/ab.po
odoo_addons/account_move_template/i18n/account_move_template.pot
odoo_addons/account_move_template/i18n/am.po
odoo_addons/account_move_template/i18n/ar.po
odoo_addons/account_move_template/i18n/bg.po
odoo_addons/account_move_template/i18n/bs.po
odoo_addons/account_move_template/i18n/ca.po
odoo_addons/account_move_template/i18n/ca_ES.po
odoo_addons/account_move_template/i18n/cs.po
odoo_addons/account_move_template/i18n/da.po
odoo_addons/account_move_template/i18n/da_DK.po
odoo_addons/account_move_template/i18n/de.po
odoo_addons/account_move_template/i18n/el_GR.po
odoo_addons/account_move_template/i18n/en_AU.po
odoo_addons/account_move_template/i18n/en_GB.po
odoo_addons/account_move_template/i18n/es.po
odoo_addons/account_move_template/i18n/es_AR.po
odoo_addons/account_move_template/i18n/es_CL.po
odoo_addons/account_move_template/i18n/es_CO.po
odoo_addons/account_move_template/i18n/es_CR.po
odoo_addons/account_move_template/i18n/es_DO.po
odoo_addons/account_move_template/i18n/es_EC.po
odoo_addons/account_move_template/i18n/es_ES.po
odoo_addons/account_move_template/i18n/es_MX.po
odoo_addons/account_move_template/i18n/es_PE.po
odoo_addons/account_move_template/i18n/es_PY.po
odoo_addons/account_move_template/i18n/es_VE.po
odoo_addons/account_move_template/i18n/et.po
odoo_addons/account_move_template/i18n/eu.po
odoo_addons/account_move_template/i18n/fa.po
odoo_addons/account_move_template/i18n/fi.po
odoo_addons/account_move_template/i18n/fr.po
odoo_addons/account_move_template/i18n/fr_CA.po
odoo_addons/account_move_template/i18n/fr_CH.po
odoo_addons/account_move_template/i18n/fr_FR.po
odoo8_addon_account_move_template-8.0.1.0.0.99.dev48.dist-info/METADATA
odoo8_addon_account_move_template-8.0.1.0.0.99.dev48.dist-info/WHEEL
odoo8_addon_account_move_template-8.0.1.0.0.99.dev48.dist-info/namespace_packages.txt
odoo8_addon_account_move_template-8.0.1.0.0.99.dev48.dist-info/top_level.txt
odoo8_addon_account_move_template-8.0.1.0.0.99.dev48.dist-info/RECORD
